odoo/addons/edi_oca/README.rst
odoo/addons/edi_oca/__init__.py
odoo/addons/edi_oca/__manifest__.py
odoo/addons/edi_oca/utils.py
odoo/addons/edi_oca/i18n/edi_oca.pot
odoo/addons/edi_oca/i18n/it.po
odoo/addons/edi_oca/migrations/18.0.1.4.0/post-migration.py
odoo/addons/edi_oca/migrations/18.0.1.5.0/end-migration.py
odoo/addons/edi_oca/readme/CONTRIBUTORS.md
odoo/addons/edi_oca/readme/DESCRIPTION.md
odoo/addons/edi_oca/static/description/icon.png
odoo/addons/edi_oca/static/description/index.html
odoo/addons/edi_oca/tests/common.py
odoo/addons/edi_oca/tests/fake_components.py
odoo/addons/edi_oca/tests/fake_models.py
odoo_addon_edi_oca-18.0.1.5.2.2.dist-info/METADATA
odoo_addon_edi_oca-18.0.1.5.2.2.dist-info/WHEEL
odoo_addon_edi_oca-18.0.1.5.2.2.dist-info/top_level.txt
odoo_addon_edi_oca-18.0.1.5.2.2.dist-info/RECORD
